[
  {
    "id": "table",
    "title": "Table",
    "order": 1,
    "path": "Table.tsx"
  },
  {
    "id": "chart",
    "title": "Chart",
    "order": 2,
    "path": "Chart.tsx"
  },
  {
    "id": "list",
    "title": "List",
    "order": 0,
    "path": "List.tsx"
  },
  {
    "id": "https://www.linkedin.com/in/andrew-shmorhun-850a76209/",
    "title": "Linked In",
    "order": 3,
    "path": "/"
  },
  {
    "id": "https://github.com/AndrewShmorhunGit/backendless/tree/development",
    "title": "Git Hub Repository",
    "order": 4,
    "path": "/"
  }
]
